capa/__init__.py
capa/engine.py
capa/exceptions.py
capa/helpers.py
capa/loader.py
capa/main.py
capa/optimizer.py
capa/perf.py
capa/version.py
capa/capabilities/__init__.py
capa/capabilities/common.py
capa/capabilities/dynamic.py
capa/capabilities/static.py
capa/features/__init__.py
capa/features/address.py
capa/features/basicblock.py
capa/features/common.py
capa/features/file.py
capa/features/insn.py
capa/features/com/__init__.py
capa/features/com/classes.py
capa/features/com/interfaces.py
capa/features/extractors/__init__.py
capa/features/extractors/base_extractor.py
capa/features/extractors/common.py
capa/features/extractors/dotnetfile.py
capa/features/extractors/elf.py
capa/features/extractors/elffile.py
capa/features/extractors/helpers.py
capa/features/extractors/loops.py
capa/features/extractors/null.py
capa/features/extractors/pefile.py
capa/features/extractors/strings.py
capa/features/extractors/binexport2/__init__.py
capa/features/extractors/binexport2/basicblock.py
capa/features/extractors/binexport2/binexport2_pb2.py
capa/features/extractors/binexport2/binexport2_pb2.pyi
capa/features/extractors/binexport2/extractor.py
capa/features/extractors/binexport2/file.py
capa/features/extractors/binexport2/function.py
capa/features/extractors/binexport2/helpers.py
capa/features/extractors/binexport2/insn.py
capa/features/extractors/binexport2/arch/__init__.py
capa/features/extractors/binexport2/arch/arm/__init__.py
capa/features/extractors/binexport2/arch/arm/helpers.py
capa/features/extractors/binexport2/arch/arm/insn.py
capa/features/extractors/binexport2/arch/intel/__init__.py
capa/features/extractors/binexport2/arch/intel/helpers.py
capa/features/extractors/binexport2/arch/intel/insn.py
capa/features/extractors/binja/__init__.py
capa/features/extractors/binja/basicblock.py
capa/features/extractors/binja/extractor.py
capa/features/extractors/binja/file.py
capa/features/extractors/binja/find_binja_api.py
capa/features/extractors/binja/function.py
flare_capa-9.3.0.dist-info/licenses/LICENSE.txt
flare_capa-9.3.0.dist-info/METADATA
flare_capa-9.3.0.dist-info/WHEEL
flare_capa-9.3.0.dist-info/entry_points.txt
flare_capa-9.3.0.dist-info/top_level.txt
flare_capa-9.3.0.dist-info/RECORD
