Metadata-Version: 2.4
Name: flare-capa
Version: 9.3.0
Summary: The FLARE team's open-source tool to identify capabilities in executable files.
Author-email: Willi Ballenthin <william.ballenthin@mandiant.com>, Moritz Raabe <moritz.raabe@mandiant.com>, Mike Hunhoff <michael.hunhoff@mandiant.com>
License: 
Project-URL: Homepage, https://github.com/mandiant/capa
Project-URL: Repository, https://github.com/mandiant/capa.git
Project-URL: Documentation, https://github.com/mandiant/capa/tree/master/doc
Project-URL: Rules, https://github.com/mandiant/capa-rules
Project-URL: Rules Documentation, https://github.com/mandiant/capa-rules/tree/master/doc
Keywords: malware analysis,reverse engineering,capability detection,software behaviors,capa,FLARE
Classifier: Development Status :: 5 - Production/Stable
Classifier: Intended Audience :: Developers
Classifier: Intended Audience :: Information Technology
Classifier: License :: OSI Approved :: Apache Software License
Classifier: Natural Language :: English
Classifier: Programming Language :: Python :: 3
Classifier: Topic :: Security
Requires-Python: >=3.10
License-File: LICENSE.txt
Requires-Dist: pyyaml>=6
Requires-Dist: colorama>=0.4
Requires-Dist: ida-settings>=3.1.0
Requires-Dist: ruamel.yaml>=0.18
Requires-Dist: pefile>=2023.2.7
Requires-Dist: pyelftools>=0.31
Requires-Dist: pydantic>=2
Requires-Dist: rich>=13
Requires-Dist: humanize>=4
Requires-Dist: protobuf>=5
Requires-Dist: msgspec>=0.18.6
Requires-Dist: xmltodict>=0.13.0
Requires-Dist: viv-utils[flirt]>=0.7.9
Requires-Dist: vivisect>=1.1.1
Requires-Dist: dncil>=1.0.2
Requires-Dist: networkx>=3
Requires-Dist: dnfile>=0.17.0
Provides-Extra: dev
Requires-Dist: pre-commit==4.2.0; extra == "dev"
Requires-Dist: pytest==8.0.0; extra == "dev"
Requires-Dist: pytest-sugar==1.1.1; extra == "dev"
Requires-Dist: pytest-instafail==0.5.0; extra == "dev"
Requires-Dist: flake8==7.3.0; extra == "dev"
Requires-Dist: flake8-bugbear==24.12.12; extra == "dev"
Requires-Dist: flake8-encodings==0.5.1; extra == "dev"
Requires-Dist: flake8-comprehensions==3.16.0; extra == "dev"
Requires-Dist: flake8-logging-format==0.9.0; extra == "dev"
Requires-Dist: flake8-no-implicit-concat==0.3.5; extra == "dev"
Requires-Dist: flake8-print==5.0.0; extra == "dev"
Requires-Dist: flake8-todos==0.3.1; extra == "dev"
Requires-Dist: flake8-simplify==0.22.0; extra == "dev"
Requires-Dist: flake8-use-pathlib==0.3.0; extra == "dev"
Requires-Dist: flake8-copyright==0.2.4; extra == "dev"
Requires-Dist: ruff==0.12.0; extra == "dev"
Requires-Dist: black==25.1.0; extra == "dev"
Requires-Dist: isort==6.0.0; extra == "dev"
Requires-Dist: mypy==1.17.1; extra == "dev"
Requires-Dist: mypy-protobuf==3.6.0; extra == "dev"
Requires-Dist: PyGithub==2.6.0; extra == "dev"
Requires-Dist: bump-my-version==1.2.4; extra == "dev"
Requires-Dist: types-backports==0.1.3; extra == "dev"
Requires-Dist: types-colorama==0.4.15.11; extra == "dev"
Requires-Dist: types-PyYAML==6.0.8; extra == "dev"
Requires-Dist: types-psutil==7.0.0.20250218; extra == "dev"
Requires-Dist: types_requests==2.32.0.20240712; extra == "dev"
Requires-Dist: types-protobuf==6.32.1.20250918; extra == "dev"
Requires-Dist: deptry==0.23.0; extra == "dev"
Provides-Extra: build
Requires-Dist: pyinstaller==6.14.1; extra == "build"
Requires-Dist: setuptools==80.9.0; extra == "build"
Requires-Dist: build==1.3.0; extra == "build"
Provides-Extra: scripts
Requires-Dist: jschema_to_python==1.2.3; extra == "scripts"
Requires-Dist: psutil==7.1.2; extra == "scripts"
Requires-Dist: stix2==3.0.1; extra == "scripts"
Requires-Dist: sarif_om==1.0.4; extra == "scripts"
Requires-Dist: requests>=2.32.4; extra == "scripts"
Dynamic: license-file
